latex_formatter/__init__.py
latex_formatter/test.py
latex_formatter/converter/__init__.py
latex_formatter/converter/converter.py
latex_formatter/utils/__init__.py
latex_formatter/utils/text_to_latex.py
latex_formatter/utils/transfer.py
latex_formatter-0.1.dist-info/METADATA
latex_formatter-0.1.dist-info/WHEEL
latex_formatter-0.1.dist-info/top_level.txt
latex_formatter-0.1.dist-info/RECORD
